custom_imports/__init__.py
custom_imports/file_module/__init__.py
custom_imports/file_module/ext_finder.py
custom_imports/file_module/loader.py
custom_imports/importer/__init__.py
custom_imports/importer/importer.py
custom_imports/importer/simple_finder.py
custom_imports/importer/simple_loader.py
custom_imports/importer/types.py
custom_imports/sample_importers/__init__.py
custom_imports/sample_importers/config_importer.py
custom_imports/sample_importers/csv_importer.py
custom_imports/sample_importers/json_importer.py
custom_imports/utils/__init__.py
custom_imports/utils/attr_dict.py
custom_imports-1.0.0.dist-info/LICENSE
custom_imports-1.0.0.dist-info/METADATA
custom_imports-1.0.0.dist-info/WHEEL
custom_imports-1.0.0.dist-info/top_level.txt
custom_imports-1.0.0.dist-info/RECORD
