Metadata-Version: 2.1
Name: custom-imports
Version: 1.0.0
Summary: Tools to hook into Python's import syntax
Home-page: https://github.com/madman-bob/python-custom-imports
Author: Robert Wright
Author-email: madman.bob@hotmail.co.uk
License: MIT
Platform: UNKNOWN
Classifier: License :: OSI Approved :: MIT License
Classifier: Programming Language :: Python :: 3
Classifier: Programming Language :: Python :: 3.6
Classifier: Programming Language :: Python :: 3.7
Classifier: Programming Language :: Python :: 3.8
Requires-Python: >=3.6
Requires-Dist: more-properties
Requires-Dist: twine
